{
  "project_info": {
    "project_number": "1046241271811",
    "firebase_url": "https://clever-move-97981.firebaseio.com",
    "project_id": "clever-move-97981",
    "storage_bucket": "clever-move-97981.appspot.com"
  },
  "client": [
    {
      "client_info": {
        "mobilesdk_app_id": "1:1046241271811:android:b8e03e63a4978c42",
        "android_client_info": {
          "package_name": "com.clevermove.android"
        }
      },
      "oauth_client": [
        {
          "client_id": "1046241271811-jshaunkhu3otr18l5fc6gga83nrcbnit.apps.googleusercontent.com",
          "client_type": 3
        }
      ],
      "api_key": [
        {
          "current_key": "AIzaSyCvc_ozYTup9-Zx3Vi_BeGjqh-cwk7yrJ0"
        }
      ],
      "services": {
        "analytics_service": {
          "status": 1
        },
        "appinvite_service": {
          "status": 1,
          "other_platform_oauth_client": []
        },
        "ads_service": {
          "status": 2
        }
      }
    }
  ],
  "configuration_version": "1"
}